configuration_maker/__init__.py
configuration_maker/main.py
configuration_maker-0.1.5.dist-info/METADATA
configuration_maker-0.1.5.dist-info/WHEEL
configuration_maker-0.1.5.dist-info/top_level.txt
configuration_maker-0.1.5.dist-info/RECORD
